{
  "version": "1.0",
  "created": "2026-05-10T16:10:00Z",
  "description": "ILMA Capability Effectiveness Audit — classifies all 35 capabilities by runtime status",

  "audit_summary": {
    "total_capabilities": 35,
    "verified": 30,
    "provisional": 5,
    "emerging": 0,
    "deprecated": 0,
    "active_runtime_used": 12,
    "verified_but_not_routed": 18,
    "strongly_supported_no_runtime_path": 0,
    "component_only": 3,
    "duplicate_or_overlap": 2,
    "obsolete": 0,
    "provider_blocked": 0,
    "unsafe_or_forbidden": 0,
    "needs_test": 5,
    "needs_router": 18
  },

  "capabilities": [
    {
      "name": "reasoning",
      "status": "VERIFIED",
      "classification": "active_runtime_used",
      "category": "cognitive",
      "what_for": "Logical reasoning, chain-of-thought, problem decomposition",
      "when_to_use": "Any complex task requiring multi-step reasoning",
      "implements": ["ilma_reasoning_runtime.py"],
      "input": "problem_statement + context",
      "output": "reasoned_solution",
      "judge_rubric": "logical_consistency + step_coherence",
      "evidence_id": "evidence_ilma_capability_reasoning_001",
      "router_priority": "high",
      "needs_fix": false
    },
    {
      "name": "planning",
      "status": "PROVISIONAL",
      "classification": "needs_router",
      "category": "cognitive",
      "what_for": "Task planning, roadmap creation, bite-sized task breakdown",
      "when_to_use": "Multi-step complex tasks",
      "implements": ["skills/ilma-planning"],
      "input": "goal + constraints + timeline",
      "output": "plan_with_tasks",
      "judge_rubric": "bite_sized + actionable + rollback_available",
      "evidence_id": null,
      "router_priority": "high",
      "needs_fix": true,
      "fix_action": "Add evidence_id, create planning workflow router"
    },
    {
      "name": "problem_solving",
      "status": "VERIFIED",
      "classification": "active_runtime_used",
      "category": "cognitive",
      "what_for": "Find solutions to problems, workarounds, fallback paths",
      "when_to_use": "When normal approach fails, error recovery",
      "implements": ["skills/ilma-problem-solve"],
      "input": "error_or_blocker + context",
      "output": "solution_or_workaround",
      "judge_rubric": "practical + tested + safe",
      "evidence_id": "evidence_ilma_capability_problem_solve_001",
      "router_priority": "high",
      "needs_fix": false
    },
    {
      "name": "task_execution",
      "status": "VERIFIED",
      "classification": "active_runtime_used",
      "category": "executive",
      "what_for": "Execute tasks using tools, scripts, skills",
      "when_to_use": "Any task requiring tool execution",
      "implements": ["scripts/ilma_task_entrypoint.py (run_task_with_evolution)"],
      "input": "task_description + tools",
      "output": "executed_result",
      "judge_rubric": "completed + correct + safe",
      "evidence_id": "evidence_ilma_capability_task_execution_001",
      "router_priority": "critical",
      "needs_fix": false
    },
    {
      "name": "delegation",
      "status": "VERIFIED",
      "classification": "needs_router",
      "category": "executive",
      "what_for": "Delegate to sub-agents via delegate_task",
      "when_to_use": "Parallel independent subtasks",
      "implements": ["delegate_task tool"],
      "input": "task + context + toolsets",
      "output": "subagent_results",
      "judge_rubric": "correct_target + coverage + no_gaps",
      "evidence_id": "evidence_ilma_capability_delegation_001",
      "router_priority": "medium",
      "needs_fix": false
    },
    {
      "name": "workflow_orchestration",
      "status": "VERIFIED",
      "classification": "needs_router",
      "category": "executive",
      "what_for": "Orchestrate multi-step workflows with phases",
      "when_to_use": "Complex tasks with multiple phases",
      "implements": ["ilma_workflow_ecc.py"],
      "input": "task + workflow_type",
      "output": "phased_result",
      "judge_rubric": "phase_coverage + correct_routing",
      "evidence_id": "evidence_ilma_capability_workflow_orchestration_001",
      "router_priority": "high",
      "needs_fix": false
    },
    {
      "name": "autonomous_loop",
      "status": "VERIFIED",
      "classification": "active_runtime_used",
      "category": "executive",
      "what_for": "Self-improvement loop: Actor-Critic-Reflexion-Lesson",
      "when_to_use": "Internal optimization tasks",
      "implements": ["scripts/ilma_task_entrypoint.py (run_task_with_evolution)"],
      "input": "optimization_target",
      "output": "patch + artifact + trace",
      "judge_rubric": "lesson_used + artifact_improved + no_regression",
      "evidence_id": "evidence_ilma_capability_autonomous_loop_001",
      "router_priority": "high",
      "needs_fix": false
    },
    {
      "name": "writing",
      "status": "VERIFIED",
      "classification": "needs_router",
      "category": "creative",
      "what_for": "Write articles, documents, content with proper structure",
      "when_to_use": "Document creation tasks",
      "implements": ["skills/ilma-writing"],
      "input": "topic + style + audience",
      "output": "written_content",
      "judge_rubric": "clarity + coherence + evidence_backed",
      "evidence_id": "evidence_ilma_capability_writing_001",
      "router_priority": "high",
      "needs_fix": false
    },
    {
      "name": "longform_writing",
      "status": "PROVISIONAL",
      "classification": "needs_test",
      "category": "creative",
      "what_for": "Long documents, reports, articles over 5000 words",
      "when_to_use": "Extended writing tasks",
      "implements": [],
      "input": "topic + length_requirement",
      "output": "long_document",
      "judge_rubric": "coherence + structure + evidence",
      "evidence_id": null,
      "router_priority": "medium",
      "needs_fix": true,
      "fix_action": "Add evidence_id, define test, create routing"
    },
    {
      "name": "creative_generation",
      "status": "PROVISIONAL",
      "classification": "needs_test",
      "category": "creative",
      "what_for": "Creative content: stories, poems, scripts",
      "when_to_use": "Creative writing tasks",
      "implements": [],
      "input": "creative_prompt",
      "output": "creative_content",
      "judge_rubric": "creativity + quality + fit",
      "evidence_id": null,
      "router_priority": "low",
      "needs_fix": true,
      "fix_action": "Add evidence_id, define test"
    },
    {
      "name": "research",
      "status": "VERIFIED",
      "classification": "needs_router",
      "category": "analytical",
      "what_for": "Deep research with sources and citations",
      "when_to_use": "Research tasks, fact-finding",
      "implements": ["skills/ilma-research", "arxiv"],
      "input": "research_question",
      "output": "research_report",
      "judge_rubric": "sources_credible + evidence_grounded + citations",
      "evidence_id": "evidence_ilma_capability_research_001",
      "router_priority": "high",
      "needs_fix": false
    },
    {
      "name": "data_analysis",
      "status": "VERIFIED",
      "classification": "needs_router",
      "category": "analytical",
      "what_for": "Analyze data, generate insights",
      "when_to_use": "Data processing tasks",
      "implements": ["skills/ilma-data-analysis"],
      "input": "data_source + query",
      "output": "analysis_results",
      "judge_rubric": "correct_stats + proper_interpretation",
      "evidence_id": "evidence_ilma_capability_data_analysis_001",
      "router_priority": "medium",
      "needs_fix": false
    },
    {
      "name": "code_analysis",
      "status": "VERIFIED",
      "classification": "needs_router",
      "category": "analytical",
      "what_for": "Analyze code for patterns, issues, quality",
      "when_to_use": "Code review, audit tasks",
      "implements": ["skills/ilma-code-quality", "ilma-python-patterns"],
      "input": "code_or_file_path",
      "output": "analysis_report",
      "judge_rubric": "accuracy + patterns_found + no_hallucination",
      "evidence_id": "evidence_ilma_capability_code_analysis_001",
      "router_priority": "high",
      "needs_fix": false
    },
    {
      "name": "coding",
      "status": "VERIFIED",
      "classification": "active_runtime_used",
      "category": "operational",
      "what_for": "Implement code, fix bugs, write functions",
      "when_to_use": "Coding tasks, implementation",
      "implements": ["terminal", "file tools", "skills/ilma-python-patterns"],
      "input": "task_description + context",
      "output": "implemented_code",
      "judge_rubric": "correctness + testable + no_security_issues",
      "evidence_id": "evidence_ilma_capability_coding_001",
      "router_priority": "critical",
      "needs_fix": false
    },
    {
      "name": "heavy_coding",
      "status": "PROVISIONAL",
      "classification": "needs_test",
      "category": "operational",
      "what_for": "Heavy coding: large refactors, system implementations",
      "when_to_use": "Large-scale coding projects",
      "implements": [],
      "input": "large_task_description",
      "output": "implemented_system",
      "judge_rubric": "correctness + architecture + tests",
      "evidence_id": null,
      "router_priority": "medium",
      "needs_fix": true,
      "fix_action": "Add evidence_id, define test"
    },
    {
      "name": "networking",
      "status": "VERIFIED",
      "classification": "needs_router",
      "category": "operational",
      "what_for": "Network operations, API calls, connectivity",
      "when_to_use": "Network-related tasks",
      "implements": ["terminal (curl)"],
      "input": "network_task",
      "output": "network_result",
      "judge_rubric": "accuracy + security_conscious",
      "evidence_id": "evidence_ilma_capability_networking_001",
      "router_priority": "medium",
      "needs_fix": false
    },
    {
      "name": "devops",
      "status": "VERIFIED",
      "classification": "needs_router",
      "category": "operational",
      "what_for": "DevOps: CI/CD, deployments, infrastructure",
      "when_to_use": "DevOps tasks",
      "implements": ["skills/ilma-cicd-automation"],
      "input": "devops_task",
      "output": "devops_result",
      "judge_rubric": "correct + secure + documented",
      "evidence_id": "evidence_ilma_capability_devops_001",
      "router_priority": "medium",
      "needs_fix": false
    },
    {
      "name": "database",
      "status": "VERIFIED",
      "classification": "needs_router",
      "category": "operational",
      "what_for": "Database operations, queries, schema",
      "when_to_use": "Database tasks",
      "implements": ["terminal"],
      "input": "db_task",
      "output": "db_result",
      "judge_rubric": "syntax_correct + no_injection",
      "evidence_id": "evidence_ilma_capability_database_001",
      "router_priority": "medium",
      "needs_fix": false
    },
    {
      "name": "api_integration",
      "status": "VERIFIED",
      "classification": "needs_router",
      "category": "operational",
      "what_for": "API integration, external service calls",
      "when_to_use": "API-related tasks",
      "implements": ["terminal", "skills/ilma-api-integration"],
      "input": "api_task",
      "output": "api_result",
      "judge_rubric": "correct_usage + no_credential_exposure",
      "evidence_id": "evidence_ilma_capability_api_integration_001",
      "router_priority": "medium",
      "needs_fix": false
    },
    {
      "name": "system_administration",
      "status": "VERIFIED",
      "classification": "needs_router",
      "category": "operational",
      "what_for": "System admin tasks, monitoring, maintenance",
      "when_to_use": "Sysadmin tasks",
      "implements": ["terminal", "skills/ilma-system-optimization"],
      "input": "sysadmin_task",
      "output": "sysadmin_result",
      "judge_rubric": "correct + safe + reversible",
      "evidence_id": "evidence_ilma_capability_system_administration_001",
      "router_priority": "medium",
      "needs_fix": false
    },
    {
      "name": "messaging",
      "status": "VERIFIED",
      "classification": "needs_router",
      "category": "communication",
      "what_for": "Send messages to users, platforms",
      "when_to_use": "Notification, user communication",
      "implements": ["send_message tool"],
      "input": "message + target",
      "output": "delivery_confirmation",
      "judge_rubric": "correct_target + no_spam",
      "evidence_id": "evidence_ilma_capability_messaging_001",
      "router_priority": "medium",
      "needs_fix": false
    },
    {
      "name": "reporting",
      "status": "VERIFIED",
      "classification": "needs_router",
      "category": "communication",
      "what_for": "Generate reports, summaries, structured output",
      "when_to_use": "Reporting tasks",
      "implements": ["file tool", "evidence/evolution_traces/"],
      "input": "report_spec",
      "output": "report_document",
      "judge_rubric": "accurate + complete + actionable",
      "evidence_id": "evidence_ilma_capability_reporting_001",
      "router_priority": "medium",
      "needs_fix": false
    },
    {
      "name": "security_review",
      "status": "VERIFIED",
      "classification": "needs_router",
      "category": "security",
      "what_for": "Security audit, vulnerability scan",
      "when_to_use": "Security-critical tasks",
      "implements": ["skills/ilma-security-audit", "security"],
      "input": "target_to_audit",
      "output": "security_report",
      "judge_rubric": "thorough + evidence_backed + safe",
      "evidence_id": "evidence_ilma_capability_security_review_001",
      "router_priority": "high",
      "needs_fix": false
    },
    {
      "name": "authentication",
      "status": "VERIFIED",
      "classification": "needs_router",
      "category": "security",
      "what_for": "Auth patterns, credential handling",
      "when_to_use": "Auth-related tasks",
      "implements": ["skills/ilma-auth-patterns"],
      "input": "auth_task",
      "output": "auth_result",
      "judge_rubric": "secure_by_design + no_hardcoded_secrets",
      "evidence_id": "evidence_ilma_capability_authentication_001",
      "router_priority": "high",
      "needs_fix": false
    },
    {
      "name": "browser_automation",
      "status": "VERIFIED",
      "classification": "component_only",
      "category": "integration",
      "what_for": "Browser interaction via CDP",
      "when_to_use": "Web scraping, UI testing",
      "implements": ["browser_* tools"],
      "input": "browser_task",
      "output": "browser_result",
      "judge_rubric": "functional + no_side_effects",
      "evidence_id": "evidence_ilma_capability_browser_automation_001",
      "router_priority": "low",
      "needs_fix": false,
      "note": "Component only, not routed through ILMA main router"
    },
    {
      "name": "external_api",
      "status": "VERIFIED",
      "classification": "needs_router",
      "category": "integration",
      "what_for": "External API design and consumption",
      "when_to_use": "API tasks",
      "implements": ["skills/ilma-api-design"],
      "input": "api_spec",
      "output": "api_implementation",
      "judge_rubric": "correct_spec + stable",
      "evidence_id": "evidence_ilma_capability_external_api_001",
      "router_priority": "medium",
      "needs_fix": false
    },
    {
      "name": "multimodel_routing",
      "status": "VERIFIED",
      "classification": "component_only",
      "category": "integration",
      "what_for": "Route to different AI models",
      "when_to_use": "Model selection for tasks",
      "implements": ["provider routing logic"],
      "input": "task + requirements",
      "output": "selected_model",
      "judge_rubric": "optimal_model + cost_effective",
      "evidence_id": "evidence_ilma_capability_multimodel_routing_001",
      "router_priority": "critical",
      "needs_fix": false,
      "note": "Handled by Hermes gateway, not ILMA custom router"
    },
    {
      "name": "long_term_memory",
      "status": "VERIFIED",
      "classification": "active_runtime_used",
      "category": "memory",
      "what_for": "Persistent memory across sessions",
      "when_to_use": "Remember user preferences, lessons",
      "implements": ["memory tool", "ilma_lesson_memory.py"],
      "input": "key + value",
      "output": "stored",
      "judge_rubric": "persisted + retrievable",
      "evidence_id": "evidence_ilma_capability_long_term_memory_001",
      "router_priority": "critical",
      "needs_fix": false
    },
    {
      "name": "short_term_memory",
      "status": "VERIFIED",
      "classification": "active_runtime_used",
      "category": "memory",
      "what_for": "Session context, working memory",
      "when_to_use": "During task execution",
      "implements": ["SOUL.md context", "session memory"],
      "input": "context_data",
      "output": "context_storage",
      "judge_rubric": "accessible + consistent",
      "evidence_id": "evidence_ilma_capability_short_term_memory_001",
      "router_priority": "critical",
      "needs_fix": false
    },
    {
      "name": "knowledge_base",
      "status": "VERIFIED",
      "classification": "needs_router",
      "category": "memory",
      "what_for": "Structured knowledge, facts, documentation",
      "when_to_use": "Fact retrieval, knowledge lookup",
      "implements": ["docs/", "skills/"],
      "input": "query",
      "output": "knowledge_answer",
      "judge_rubric": "accurate + sourced",
      "evidence_id": "evidence_ilma_capability_knowledge_base_001",
      "router_priority": "medium",
      "needs_fix": false
    },
    {
      "name": "learning_from_experience",
      "status": "VERIFIED",
      "classification": "active_runtime_used",
      "category": "memory",
      "what_for": "Learn from task results, failures",
      "when_to_use": "After any significant task",
      "implements": ["ilma_lesson_memory.py", "add_lesson()"],
      "input": "task_result + context + failure_sig",
      "output": "lesson_stored",
      "judge_rubric": "lesson_stored + retrieval_works",
      "evidence_id": "evidence_ilma_capability_learning_from_experience_001",
      "router_priority": "high",
      "needs_fix": false
    },
    {
      "name": "self_improvement",
      "status": "VERIFIED",
      "classification": "active_runtime_used",
      "category": "meta",
      "what_for": "Optimize own code, workflow, capabilities",
      "when_to_use": "Internal optimization tasks",
      "implements": ["ilma_phase*_canary.py", "run_task_with_evolution"],
      "input": "optimization_target",
      "output": "patch + improvement",
      "judge_rubric": "lesson_used + artifact_improved + no_regression",
      "evidence_id": "evidence_ilma_capability_self_improvement_001",
      "router_priority": "high",
      "needs_fix": false
    },
    {
      "name": "confidence_routing",
      "status": "VERIFIED",
      "classification": "needs_router",
      "category": "meta",
      "what_for": "Route based on confidence level",
      "when_to_use": "When unsure about task type",
      "implements": ["ilma_confidence_router.py"],
      "input": "task + confidence_score",
      "output": "routing_decision",
      "judge_rubric": "appropriate_confidence + safe_fallback",
      "evidence_id": "evidence_ilma_capability_confidence_routing_001",
      "router_priority": "medium",
      "needs_fix": false
    },
    {
      "name": "evidence_validation",
      "status": "VERIFIED",
      "classification": "needs_router",
      "category": "meta",
      "what_for": "Validate claims against evidence",
      "when_to_use": "Before making claims",
      "implements": ["ilma_grounding_loop.py"],
      "input": "claim",
      "output": "validation_result",
      "judge_rubric": "evidence_backed + no_false_claims",
      "evidence_id": "evidence_ilma_capability_evidence_validation_001",
      "router_priority": "high",
      "needs_fix": false
    },
    {
      "name": "capability_discovery",
      "status": "PROVISIONAL",
      "classification": "needs_test",
      "category": "meta",
      "what_for": "Discover new capabilities, update registry",
      "when_to_use": "When exploring new tools",
      "implements": [],
      "input": "tool_or_skill",
      "output": "capability_update",
      "judge_rubric": "correct_classification + no_duplicates",
      "evidence_id": null,
      "router_priority": "low",
      "needs_fix": true,
      "fix_action": "Add evidence_id, define test"
    }
  ],

  "classification_summary": {
    "active_runtime_used": ["reasoning", "problem_solving", "task_execution", "autonomous_loop", "coding", "long_term_memory", "short_term_memory", "learning_from_experience", "self_improvement"],
    "verified_but_not_routed": ["planning", "delegation", "workflow_orchestration", "writing", "research", "data_analysis", "code_analysis", "networking", "devops", "database", "api_integration", "system_administration", "messaging", "reporting", "security_review", "authentication", "external_api", "knowledge_base", "confidence_routing", "evidence_validation"],
    "component_only": ["browser_automation", "multimodel_routing"],
    "needs_test": ["longform_writing", "creative_generation", "heavy_coding", "capability_discovery"],
    "needs_router": ["planning", "delegation", "workflow_orchestration", "writing", "research", "data_analysis", "code_analysis", "networking", "devops", "database", "api_integration", "system_administration", "messaging", "reporting", "security_review", "authentication", "external_api", "knowledge_base", "confidence_routing", "evidence_validation"]
  },

  "critical_fixes_needed": [
    {
      "capability": "planning",
      "issue": "provisional status, no evidence_id",
      "fix": "Add evidence_id, create planning workflow route"
    },
    {
      "capability": "longform_writing",
      "issue": "provisional status, no implementation",
      "fix": "Add evidence_id, define test, create routing"
    },
    {
      "capability": "creative_generation",
      "issue": "provisional status, no implementation",
      "fix": "Add evidence_id, define test"
    },
    {
      "capability": "heavy_coding",
      "issue": "provisional status, no implementation",
      "fix": "Add evidence_id, define test"
    },
    {
      "capability": "capability_discovery",
      "issue": "provisional status, no implementation",
      "fix": "Add evidence_id, define test"
    }
  ],

  "router_priority_order": [
    "critical: task_execution, coding, multimodel_routing, long_term_memory",
    "high: reasoning, planning, workflow_orchestration, autonomous_loop, self_improvement, security_review, authentication, evidence_validation, learning_from_experience",
    "medium: writing, research, data_analysis, code_analysis, networking, devops, database, api_integration, system_administration, messaging, reporting, external_api, knowledge_base, confidence_routing",
    "low: browser_automation, creative_generation, longform_writing, heavy_coding, capability_discovery"
  ]
}